AMR/__init__.py
AMR/datasets.py
AMR/functions.py
amr-3.0.1.9016.dist-info/METADATA
amr-3.0.1.9016.dist-info/WHEEL
amr-3.0.1.9016.dist-info/top_level.txt
amr-3.0.1.9016.dist-info/RECORD
