Metadata-Version: 2.4
Name: AMR
Version: 3.0.1.9016
Summary: A Python wrapper for the AMR R package
Home-page: https://github.com/msberends/AMR
Author: Matthijs Berends
Author-email: m.s.berends@umcg.nl
License: GPL 2
Project-URL: Bug Tracker, https://github.com/msberends/AMR/issues
Classifier: Programming Language :: Python :: 3
Classifier: Operating System :: OS Independent
Requires-Python: >=3.6
Requires-Dist: rpy2
Requires-Dist: numpy
Requires-Dist: pandas
Dynamic: author
Dynamic: author-email
Dynamic: classifier
Dynamic: description
Dynamic: description-content-type
Dynamic: home-page
Dynamic: license
Dynamic: project-url
Dynamic: requires-dist
Dynamic: requires-python
Dynamic: summary
